LICENSE
MANIFEST.in
README.rst
setup.py
channels_presence/__init__.py
channels_presence/admin.py
channels_presence/apps.py
channels_presence/channels.py
channels_presence/decorators.py
channels_presence/models.py
channels_presence/signals.py
channels_presence/tasks.py
channels_presence/tests.py
channels_presence/views.py
channels_presence/management/__init__.py
channels_presence/management/commands/__init__.py
channels_presence/management/commands/prune_presences.py
channels_presence/management/commands/prune_rooms.py
channels_presence/migrations/0001_initial.py
channels_presence/migrations/__init__.py
django_channels_presence.egg-info/PKG-INFO
django_channels_presence.egg-info/SOURCES.txt
django_channels_presence.egg-info/dependency_links.txt
django_channels_presence.egg-info/top_level.txt
docs/Makefile
docs/conf.py
docs/index.rst
docs/make.bat
docs/usage.rst